mozuma/__init__.py
mozuma/__main__.py
mozuma/_build_version.py
mozuma/py.typed
mozuma/runners.py
mozuma/states.py
mozuma/testing.py
mozuma/callbacks/__init__.py
mozuma/callbacks/base.py
mozuma/callbacks/memory.py
mozuma/callbacks/states.py
mozuma/cli/__init__.py
mozuma/cli/checks.py
mozuma/cli/helpers.py
mozuma/cli/ls.py
mozuma/cli/run.py
mozuma/cli/types.py
mozuma/helpers/__init__.py
mozuma/helpers/files.py
mozuma/helpers/gdrive.py
mozuma/helpers/ignite.py
mozuma/helpers/images.py
mozuma/helpers/numpy.py
mozuma/helpers/torch.py
mozuma/helpers/torchvision.py
mozuma/labels/__init__.py
mozuma/labels/base.py
mozuma/labels/imagenet.py
mozuma/labels/places.py
mozuma/labels/places_io.py
mozuma/labels/vinvl.py
mozuma/labels/vinvl_attributes.py
mozuma/models/__init__.py
mozuma/models/types.py
mozuma/models/arcface/__init__.py
mozuma/models/arcface/modules.py
mozuma/models/arcface/normalized_faces.npy
mozuma/models/arcface/pretrained.py
mozuma/models/arcface/stores.py
mozuma/models/arcface/transforms.py
mozuma/models/arcface/utils.py
mozuma/models/classification/__init__.py
mozuma/models/classification/modules.py
mozuma/models/clip/__init__.py
mozuma/models/clip/base.py
mozuma/models/clip/image.py
mozuma/models/clip/list.py
mozuma/models/clip/parameters.py
mozuma/models/clip/pretrained.py
mozuma/models/clip/stores.py
mozuma/models/clip/text.py
mozuma/models/clip/transforms.py
mozuma/models/clip/utils.py
mozuma/models/densenet/__init__.py
mozuma/models/densenet/modules.py
mozuma/models/densenet/pretrained.py
mozuma/models/densenet/stores.py
mozuma/models/keyframes/__init__.py
mozuma/models/keyframes/datasets.py
mozuma/models/keyframes/encoders.py
mozuma/models/keyframes/keyframes.py
mozuma/models/keyframes/pretrained.py
mozuma/models/keyframes/selectors.py
mozuma/models/keyframes/transforms.py
mozuma/models/keyframes/types.py
mozuma/models/magface/__init__.py
mozuma/models/magface/modules.py
mozuma/models/magface/pretrained.py
mozuma/models/magface/stores.py
mozuma-0.9.0.dist-info/LICENSE
mozuma-0.9.0.dist-info/METADATA
mozuma-0.9.0.dist-info/WHEEL
mozuma-0.9.0.dist-info/top_level.txt
mozuma-0.9.0.dist-info/RECORD
